{
  "total_wall_interactions": 11944,
  "by_part": {
    "6": {
      "reflected_specular": 5221,
      "reflected_diffuse": 2287,
      "stuck": 643
    },
    "11": {
      "reflected_specular": 20,
      "reflected_diffuse": 9,
      "stuck": 10
    },
    "12": {
      "reflected_diffuse": 48,
      "reflected_specular": 110,
      "stuck": 19
    },
    "1": {
      "reflected_diffuse": 725,
      "reflected_specular": 2088,
      "stuck": 753
    },
    "3": {
      "reflected_specular": 2,
      "stuck": 1
    },
    "4": {
      "reflected_specular": 5,
      "reflected_diffuse": 2,
      "stuck": 1
    }
  },
  "by_outcome": {
    "reflected_specular": 7446,
    "reflected_diffuse": 3071,
    "stuck": 1427
  },
  "by_wall_mode": {
    "mixed_specular_diffuse": 11944
  }
}