{
  "output_root": "c:\\Users\\user\\Desktop\\particle_simulation\\demo_output\\integrator_compare_20260403_post_etd2polyline_10k",
  "comparison_csv": "c:\\Users\\user\\Desktop\\particle_simulation\\demo_output\\integrator_compare_20260403_post_etd2polyline_10k\\integrator_prod10k_comparison.csv",
  "rows": [
    {
      "integrator": "drag_relaxation",
      "runtime_s": 18.138295,
      "released_count": 10000,
      "stuck_count": 1811,
      "absorbed_count": 0,
      "escaped_count": 0,
      "primary_hit_count": 15551,
      "edge_hit_count": 15551,
      "triangle_hit_count": 0,
      "bisection_fallback_count": 17,
      "unresolved_crossing_count": 0,
      "multi_hit_events_count": 3492,
      "max_hits_reached_count": 2067,
      "collision_reintegrated_segments_count": 11570,
      "adaptive_substep_segments_count": 0,
      "adaptive_substep_trigger_count": 0,
      "etd2_polyline_checks_count": 0,
      "etd2_midpoint_outside_count": 0,
      "etd2_polyline_hit_count": 0,
      "etd2_polyline_fallback_count": 0
    },
    {
      "integrator": "etd",
      "runtime_s": 17.750245,
      "released_count": 10000,
      "stuck_count": 1816,
      "absorbed_count": 0,
      "escaped_count": 0,
      "primary_hit_count": 15316,
      "edge_hit_count": 15316,
      "triangle_hit_count": 0,
      "bisection_fallback_count": 53,
      "unresolved_crossing_count": 0,
      "multi_hit_events_count": 3450,
      "max_hits_reached_count": 2014,
      "collision_reintegrated_segments_count": 11423,
      "adaptive_substep_segments_count": 0,
      "adaptive_substep_trigger_count": 0,
      "etd2_polyline_checks_count": 0,
      "etd2_midpoint_outside_count": 0,
      "etd2_polyline_hit_count": 0,
      "etd2_polyline_fallback_count": 0
    },
    {
      "integrator": "etd2",
      "runtime_s": 24.324778,
      "released_count": 10000,
      "stuck_count": 1358,
      "absorbed_count": 0,
      "escaped_count": 0,
      "primary_hit_count": 10811,
      "edge_hit_count": 10811,
      "triangle_hit_count": 0,
      "bisection_fallback_count": 15,
      "unresolved_crossing_count": 0,
      "multi_hit_events_count": 2410,
      "max_hits_reached_count": 1395,
      "collision_reintegrated_segments_count": 7985,
      "adaptive_substep_segments_count": 0,
      "adaptive_substep_trigger_count": 0,
      "etd2_polyline_checks_count": 11130,
      "etd2_midpoint_outside_count": 2215,
      "etd2_polyline_hit_count": 10811,
      "etd2_polyline_fallback_count": 15
    }
  ]
}